nthuqf/__init__.py
nthuqf/m1.py
nthuqf/m2.py
nthuqf-0.1.2.dist-info/LICENSE
nthuqf-0.1.2.dist-info/METADATA
nthuqf-0.1.2.dist-info/WHEEL
nthuqf-0.1.2.dist-info/top_level.txt
nthuqf-0.1.2.dist-info/RECORD
